yeti_switch_api/__init__.py
yeti_switch_api/api/__init__.py
yeti_switch_api/api/client.py
yeti_switch_api/common/__init__.py
yeti_switch_api/common/auth.py
yeti_switch_api/orm/__init__.py
yeti_switch_api/orm/account.py
yeti_switch_api/orm/base_model.py
yeti_switch_api/orm/contact.py
yeti_switch_api/orm/contractor.py
yeti_switch_api/orm/country.py
yeti_switch_api/orm/customers_auth.py
yeti_switch_api/orm/dialpeer.py
yeti_switch_api/orm/gateway.py
yeti_switch_api/orm/gateway_group.py
yeti_switch_api/orm/invoice.py
yeti_switch_api/orm/invoice_originated_destination.py
yeti_switch_api/orm/invoice_originated_network.py
yeti_switch_api/orm/invoice_template.py
yeti_switch_api/orm/invoice_terminated_destination.py
yeti_switch_api/orm/invoice_terminated_network.py
yeti_switch_api/orm/network.py
yeti_switch_api/orm/network_type.py
yeti_switch_api/orm/numberlist.py
yeti_switch_api/orm/numberlist_item.py
yeti_switch_api/orm/orm_client.py
yeti_switch_api/orm/package_counter.py
yeti_switch_api/orm/pop.py
yeti_switch_api/orm/rateplan.py
yeti_switch_api/orm/routing_plan.py
yeti_switch_api/orm/routing_tag.py
yeti_switch_api/orm/smtp_connection.py
yeti_switch_api/orm/timezone.py
yeti_switch_api-1.2.1.dist-info/LICENSE
yeti_switch_api-1.2.1.dist-info/METADATA
yeti_switch_api-1.2.1.dist-info/WHEEL
yeti_switch_api-1.2.1.dist-info/top_level.txt
yeti_switch_api-1.2.1.dist-info/RECORD
