Metadata-Version: 2.1
Name: yeti-switch-api
Version: 1.2.1
Summary: Yeti-web Admin API SDK
Home-page: https://github.com/senid231/yeti-admin-python
Author: Denys Talakevych
Author-email: <senid231@gmail.com>
License: MIT
Project-URL: Bug Tracker, https://github.com/senid231/yeti-admin-python/issues
Keywords: yeti-switch,yeti-web
Classifier: Intended Audience :: Developers
Classifier: Programming Language :: Python :: 3
Classifier: License :: OSI Approved :: MIT License
Classifier: Operating System :: OS Independent
Classifier: Topic :: Software Development :: Libraries :: Python Modules
Requires-Python: >=3.7
License-File: LICENSE
Requires-Dist: jsonapi-requests
Requires-Dist: requests
